
{
  "products": [
    {
      "id": 1,
      "name": "Diamond Solitaire Ring",
      "price": 2499,
      "category": "rings",
      "image": "https://images.unsplash.com/photo-1605100804763-247f67b3557e?auto=format&fit=crop&w=800&q=80",
      "description": "Classic diamond solitaire ring in 18k white gold",
      "isNew": true,
      "isBestSeller": false,
      "stock": 5,
      "material": "gold"
    },
    {
      "id": 2,
      "name": "Pearl Drop Earrings",
      "price": 899,
      "category": "earrings",
      "image": "https://images.unsplash.com/photo-1535632066927-ab7c9ab60908?auto=format&fit=crop&w=800&q=80",
      "description": "Elegant freshwater pearl drop earrings",
      "isNew": false,
      "isBestSeller": true,
      "stock": 12,
      "material": "silver"
    },
    {
      "id": 3,
      "name": "Gold Chain Necklace",
      "price": 1299,
      "category": "necklaces",
      "image": "https://images.unsplash.com/photo-1515562141207-7a88fb7ce338?auto=format&fit=crop&w=800&q=80",
      "description": "Delicate 14k gold chain necklace",
      "isNew": true,
      "isBestSeller": false,
      "stock": 8,
      "material": "gold"
    },
    {
      "id": 4,
      "name": "Tennis Bracelet",
      "price": 3499,
      "category": "bracelets",
      "image": "https://images.unsplash.com/photo-1611591437281-460bfbe1220a?auto=format&fit=crop&w=800&q=80",
      "description": "Classic diamond tennis bracelet",
      "isNew": false,
      "isBestSeller": true,
      "stock": 3,
      "material": "gold"
    },
    {
      "id": 5,
      "name": "Emerald Pendant",
      "price": 1899,
      "category": "necklaces",
      "image": "https://images.unsplash.com/photo-1599643478518-a784e5dc4c8f?auto=format&fit=crop&w=800&q=80",
      "description": "Stunning emerald pendant with gold chain",
      "isNew": true,
      "isBestSeller": false,
      "stock": 6,
      "material": "gold"
    },
    {
      "id": 6,
      "name": "Rose Gold Hoops",
      "price": 699,
      "category": "earrings",
      "image": "https://images.unsplash.com/photo-1617038260897-41a1f14a8ca0?auto=format&fit=crop&w=800&q=80",
      "description": "Modern rose gold hoop earrings",
      "isNew": false,
      "isBestSeller": true,
      "stock": 15,
      "material": "gold"
    },
    {
      "id": 7,
      "name": "Sapphire Eternity Ring",
      "price": 2899,
      "category": "rings",
      "image": "https://images.unsplash.com/photo-1549388604-817d15aa0968?auto=format&fit=crop&w=800&q=80",
      "description": "Blue sapphire eternity ring in platinum",
      "isNew": true,
      "isBestSeller": false,
      "stock": 4,
      "material": "platinum"
    },
    {
      "id": 8,
      "name": "Diamond Stud Earrings",
      "price": 1599,
      "category": "earrings",
      "image": "https://images.unsplash.com/photo-1588444837495-c6c080964dd8?auto=format&fit=crop&w=800&q=80",
      "description": "Classic diamond stud earrings",
      "isNew": false,
      "isBestSeller": true,
      "stock": 10,
      "material": "gold"
    },
    {
      "id": 9,
      "name": "Charm Bracelet",
      "price": 899,
      "category": "bracelets",
      "image": "https://images.unsplash.com/photo-1573408301185-9146fe634ad0?auto=format&fit=crop&w=800&q=80",
      "description": "Sterling silver charm bracelet",
      "isNew": false,
      "isBestSeller": false,
      "stock": 7,
      "material": "silver"
    },
    {
      "id": 10,
      "name": "Vintage Art Deco Ring",
      "price": 3299,
      "category": "rings",
      "image": "https://images.unsplash.com/photo-1605100804763-247f67b3557e?auto=format&fit=crop&w=600&q=80",
      "description": "1920s inspired art deco diamond ring",
      "isNew": true,
      "isBestSeller": false,
      "stock": 2,
      "material": "platinum"
    },
    {
      "id": 11,
      "name": "Moonstone Pendant",
      "price": 1249,
      "category": "necklaces",
      "image": "https://images.unsplash.com/photo-1599643478518-a784e5dc4c8f?auto=format&fit=crop&w=600&q=80",
      "description": "Mystical moonstone pendant in silver setting",
      "isNew": true,
      "isBestSeller": false,
      "stock": 8,
      "material": "silver"
    },
    {
      "id": 12,
      "name": "Ruby Heart Necklace",
      "price": 2199,
      "category": "necklaces",
      "image": "https://images.unsplash.com/photo-1515562141207-7a88fb7ce338?auto=format&fit=crop&w=600&q=80",
      "description": "Romantic ruby heart pendant with delicate chain",
      "isNew": false,
      "isBestSeller": true,
      "stock": 6,
      "material": "gold"
    },
    {
      "id": 13,
      "name": "Infinity Bracelet",
      "price": 1599,
      "category": "bracelets",
      "image": "https://images.unsplash.com/photo-1611591437281-460bfbe1220a?auto=format&fit=crop&w=600&q=80",
      "description": "Diamond infinity symbol bracelet",
      "isNew": true,
      "isBestSeller": false,
      "stock": 5,
      "material": "gold"
    },
    {
      "id": 14,
      "name": "Turquoise Drop Earrings",
      "price": 749,
      "category": "earrings",
      "image": "https://images.unsplash.com/photo-1535632066927-ab7c9ab60908?auto=format&fit=crop&w=600&q=80",
      "description": "Bohemian turquoise drop earrings",
      "isNew": false,
      "isBestSeller": false,
      "stock": 11,
      "material": "silver"
    },
    {
      "id": 15,
      "name": "Cocktail Statement Ring",
      "price": 1899,
      "category": "rings",
      "image": "https://images.unsplash.com/photo-1549388604-817d15aa0968?auto=format&fit=crop&w=600&q=80",
      "description": "Bold cocktail ring with mixed gemstones",
      "isNew": true,
      "isBestSeller": false,
      "stock": 4,
      "material": "gold"
    },
    {
      "id": 16,
      "name": "Pearl Strand Necklace",
      "price": 1799,
      "category": "necklaces",
      "image": "https://images.unsplash.com/photo-1506630448388-4e683c67ddb0?auto=format&fit=crop&w=600&q=80",
      "description": "Classic cultured pearl strand necklace",
      "isNew": false,
      "isBestSeller": true,
      "stock": 9,
      "material": "silver"
    },
    {
      "id": 17,
      "name": "Geometric Cuff Bracelet",
      "price": 999,
      "category": "bracelets",
      "image": "https://images.unsplash.com/photo-1573408301185-9146fe634ad0?auto=format&fit=crop&w=600&q=80",
      "description": "Modern geometric gold cuff bracelet",
      "isNew": true,
      "isBestSeller": false,
      "stock": 7,
      "material": "gold"
    },
    {
      "id": 18,
      "name": "Chandelier Earrings",
      "price": 1349,
      "category": "earrings",
      "image": "https://images.unsplash.com/photo-1617038260897-41a1f14a8ca0?auto=format&fit=crop&w=600&q=80",
      "description": "Elegant crystal chandelier earrings",
      "isNew": false,
      "isBestSeller": true,
      "stock": 6,
      "material": "gold"
    },
    {
      "id": 19,
      "name": "Amethyst Cluster Ring",
      "price": 1199,
      "category": "rings",
      "image": "https://images.unsplash.com/photo-1543294001-f7cd5d7fb95d?auto=format&fit=crop&w=600&q=80",
      "description": "Natural amethyst cluster cocktail ring",
      "isNew": true,
      "isBestSeller": false,
      "stock": 5,
      "material": "silver"
    },
    {
      "id": 20,
      "name": "Layered Chain Necklace Set",
      "price": 899,
      "category": "necklaces",
      "image": "https://images.unsplash.com/photo-1515562141207-7a88fb7ce338?auto=format&fit=crop&w=600&q=80",
      "description": "Trendy layered chain necklace set",
      "isNew": true,
      "isBestSeller": false,
      "stock": 12,
      "material": "gold"
    }
  ]
}
